simple_json_utils_by_speedy/JsonUtils.py
simple_json_utils_by_speedy/__init__.py
simple_json_utils_by_speedy-0.1.1.dist-info/licenses/LICENSE
simple_json_utils_by_speedy-0.1.1.dist-info/METADATA
simple_json_utils_by_speedy-0.1.1.dist-info/WHEEL
simple_json_utils_by_speedy-0.1.1.dist-info/top_level.txt
simple_json_utils_by_speedy-0.1.1.dist-info/RECORD
