Metadata-Version: 2.4
Name: simple-json-utils-by-speedy
Version: 0.1.1
Summary: Simple JSON utils for small projects, ideal for students.
Author-email: "Marcin Kotowski (Speedy)" <marcin.kotowski2k09@gmail.com>
License: MIT
Classifier: Programming Language :: Python :: 3
Classifier: License :: OSI Approved :: MIT License
Classifier: Operating System :: OS Independent
Requires-Python: >=3.10
License-File: LICENSE
Dynamic: license-file
